LICENSE
MANIFEST.in
README.rst
setup.py
eagleeye/__init__.py
eagleeye/cli.py
eagleeye/precheck.py
eagleeye/selchrome.py
eagleeye/utils.py
eagleeye_te.egg-info/PKG-INFO
eagleeye_te.egg-info/SOURCES.txt
eagleeye_te.egg-info/dependency_links.txt
eagleeye_te.egg-info/entry_points.txt
eagleeye_te.egg-info/requires.txt
eagleeye_te.egg-info/top_level.txt