Metadata-Version: 1.1
Name: eagleeye-te
Version: 0.1.2
Summary: Distributed tool for screenshotting webpages.
Home-page: https://github.com/PaulMcMillan/eagleeye
Author: Paul McMillan
Author-email: paul@mcmillan.ws
License: Simplified BSD
Platform: UNKNOWN
Classifier: Environment :: Console
Classifier: Intended Audience :: Developers
Classifier: License :: OSI Approved :: BSD License
Classifier: Operating System :: POSIX
Classifier: Programming Language :: Python :: 2.7
Classifier: Programming Language :: Python :: Implementation :: CPython
Classifier: Programming Language :: Python :: Implementation :: PyPy
